nomiracl/__init__.py
nomiracl/logging.py
nomiracl/util.py
nomiracl/dataset/__init__.py
nomiracl/dataset/data_loader.py
nomiracl/dataset/util.py
nomiracl/eval/__init__.py
nomiracl/eval/metrics.py
nomiracl/generation/__init__.py
nomiracl/generation/anyscale.py
nomiracl/generation/azure.py
nomiracl/generation/base.py
nomiracl/generation/cohere.py
nomiracl/generation/huggingface.py
nomiracl/generation/openai.py
nomiracl/generation/utils.py
nomiracl/generation/vllm.py
nomiracl/prompts/__init__.py
nomiracl/prompts/template.py
nomiracl/prompts/utils.py
nomiracl-1.0.0.dist-info/LICENSE
nomiracl-1.0.0.dist-info/METADATA
nomiracl-1.0.0.dist-info/WHEEL
nomiracl-1.0.0.dist-info/top_level.txt
nomiracl-1.0.0.dist-info/RECORD
