Metadata-Version: 2.1
Name: nomiracl
Version: 1.0.0
Summary: Multilingual Relevance Assessment for RAG Applications
Author-email: Nandan Thakur <nandant@gmail.com>
Maintainer-email: Nandan Thakur <nandant@gmail.com>
License: Apache 2.0
Project-URL: Homepage, https://nomiracl.github.io
Project-URL: Repository, https://github.com/project-miracl/nomiracl
Keywords: Transformer Networks,PyTorch,NLP,deep learning,LLM,Hallucination,Relevance,Multilingual
Classifier: Intended Audience :: Science/Research
Classifier: License :: OSI Approved :: MIT License
Classifier: Programming Language :: Python :: 3.8
Classifier: Programming Language :: Python :: 3.9
Classifier: Programming Language :: Python :: 3.10
Classifier: Programming Language :: Python :: 3.11
Classifier: Programming Language :: Python :: 3.12
Classifier: Topic :: Scientific/Engineering :: Artificial Intelligence
Requires-Python: >=3.8
License-File: LICENSE
Requires-Dist: torch
Requires-Dist: cohere
Requires-Dist: openai
Requires-Dist: tiktoken
Requires-Dist: datasets
Requires-Dist: transformers
Provides-Extra: hf
Requires-Dist: accelerate>=0.20.3; extra == "hf"
Requires-Dist: peft; extra == "hf"
Requires-Dist: bitsandbytes; extra == "hf"
Provides-Extra: vllm
Requires-Dist: vllm; extra == "vllm"
Provides-Extra: dev
Requires-Dist: pytest; extra == "dev"
Requires-Dist: pytest-cov; extra == "dev"
Requires-Dist: pre-commit; extra == "dev"
